{
  "cli": {
    "version": ">= 0.38.3"
  },
  "build": {
    "base": {
      "node": "16.13.0"
    },
    "development": {
      "extends": "base",
      "distribution": "internal",
      "android": {
        "gradleCommand": ":app:assembleDebug"
      },
      "ios": {
        "buildConfiguration": "Debug"
      }
    },
    "preview": {
      "extends": "base",
      "distribution": "internal"
    },
    "production": {
      "extends": "base"
    }
  },
  "submit": {
    "production": {}
  }
}
